{
    "Ar36": {
        "error": 0.00078957196939163671, 
        "fit": "parabolic", 
        "value": 0.0006573037788185597
    }, 
    "Ar37": {
        "error": 0.13484514321953772, 
        "fit": "linear", 
        "value": 0.032767449555023927
    }, 
    "Ar38": {
        "error": 0.13085448498661537, 
        "fit": "linear", 
        "value": 0.0019909606445955557
    }, 
    "Ar39": {
        "error": 0.056975772465835989, 
        "fit": "parabolic", 
        "value": 0.018648049088591953
    }, 
    "Ar40": {
        "error": 0.13259781089180686, 
        "fit": "parabolic", 
        "value": 0.23662843173559719
    }, 
    "Ar41": {
        "error": 0.12748512806105336, 
        "fit": "average_SEM", 
        "value": -0.18167719334946014
    }
}