{
    "Ar36": {
        "error": 0.00076120536623277668, 
        "fit": "parabolic", 
        "value": 0.00080324910873713759
    }, 
    "Ar37": {
        "error": 0.13008123727155355, 
        "fit": "linear", 
        "value": -0.34989008807188826
    }, 
    "Ar38": {
        "error": 0.18349895034420169, 
        "fit": "linear", 
        "value": -0.33028800736032116
    }, 
    "Ar39": {
        "error": 0.05909756928594579, 
        "fit": "parabolic", 
        "value": 0.014671868721428416
    }, 
    "Ar40": {
        "error": 0.13175195862813188, 
        "fit": "parabolic", 
        "value": -0.13575332493822387
    }, 
    "Ar41": {
        "error": 0.1265046215237855, 
        "fit": "average_SEM", 
        "value": -0.44664271749556067
    }
}