{
    "AX": {
        "error": 0.05214605402314759, 
        "fit": "average_SEM", 
        "value": -0.02525579946801978
    }, 
    "CDD": {
        "error": 0.00019291801815452764, 
        "fit": "average_SEM", 
        "value": 0.00023141372100023242
    }, 
    "H1": {
        "error": 0.12287907005045341, 
        "fit": "average_SEM", 
        "value": 0.14593928426038474
    }, 
    "H2": {
        "error": 0.1262197892371847, 
        "fit": "average_SEM", 
        "value": -0.08029686493076345
    }, 
    "L1": {
        "error": 0.12956573408931826, 
        "fit": "average_SEM", 
        "value": 0.11764879426530873
    }, 
    "L2": {
        "error": 0.12983881668650804, 
        "fit": "average_SEM", 
        "value": 0.14318721613720603
    }
}