{
    "AX": {
        "error": 0.05829994805527067, 
        "fit": "average_SEM", 
        "value": -0.006621870042727096
    }, 
    "CDD": {
        "error": 0.00014714872197787158, 
        "fit": "average_SEM", 
        "value": 0.00015080894178633267
    }, 
    "H1": {
        "error": 0.1282920791592801, 
        "fit": "average_SEM", 
        "value": -0.06986500189523212
    }, 
    "H2": {
        "error": 0.11189772206670816, 
        "fit": "average_SEM", 
        "value": -0.07946045823288538
    }, 
    "L1": {
        "error": 0.19696874712753318, 
        "fit": "average_SEM", 
        "value": -0.11190507495969844
    }, 
    "L2": {
        "error": 0.13674008407988383, 
        "fit": "average_SEM", 
        "value": -0.14108783413345616
    }
}