{
    "AX": {
        "error": 0.05353362608974281, 
        "fit": "average_SEM", 
        "value": -0.015141367491499599
    }, 
    "CDD": {
        "error": 3.671761688049599e-05, 
        "fit": "average_SEM", 
        "value": 9.100539561283464e-06
    }, 
    "H1": {
        "error": 0.1365998038304254, 
        "fit": "average_SEM", 
        "value": 0.042073519018155515
    }, 
    "H2": {
        "error": 0.12792833205992674, 
        "fit": "average_SEM", 
        "value": 0.008969674944334352
    }, 
    "L1": {
        "error": 0.14202780323880573, 
        "fit": "average_SEM", 
        "value": 0.0041196791590967525
    }, 
    "L2": {
        "error": 0.11954713280091099, 
        "fit": "average_SEM", 
        "value": 0.010048129815307524
    }
}