{
    "AX": {
        "error": 0.05679163001222892, 
        "fit": "average_SEM", 
        "value": 0.02162899362204674
    }, 
    "CDD": {
        "error": 8.151230865849277e-05, 
        "fit": "average_SEM", 
        "value": 5.6025001686066386e-05
    }, 
    "H1": {
        "error": 0.1151048685008016, 
        "fit": "average_SEM", 
        "value": -0.624472376704216
    }, 
    "H2": {
        "error": 0.11544592162872452, 
        "fit": "average_SEM", 
        "value": -0.48315724010268846
    }, 
    "L1": {
        "error": 0.11639045740935566, 
        "fit": "average_SEM", 
        "value": -0.5266378134489059
    }, 
    "L2": {
        "error": 0.29800364245181116, 
        "fit": "average_SEM", 
        "value": -0.2706802606893082
    }
}