{
    "AX": {
        "error": 0.057761368770438457, 
        "fit": "average_SEM", 
        "value": 0.009717209975982162
    }, 
    "CDD": {
        "error": 0.00011705426938540712, 
        "fit": "average_SEM", 
        "value": 0.00010270608933448481
    }, 
    "H1": {
        "error": 0.145569165886909, 
        "fit": "average_SEM", 
        "value": -0.2532853701481751
    }, 
    "H2": {
        "error": 0.11716614990847753, 
        "fit": "average_SEM", 
        "value": -0.4703786808997393
    }, 
    "L1": {
        "error": 0.1755307222451507, 
        "fit": "average_SEM", 
        "value": -0.32981506790577747
    }, 
    "L2": {
        "error": 0.12493141403280644, 
        "fit": "average_SEM", 
        "value": -0.4070400926284492
    }
}