{
    "AX": {
        "error": 0.059004631265011494, 
        "fit": "average_SEM", 
        "value": 0.011390347423730417
    }, 
    "CDD": {
        "error": 0.00010872000831983438, 
        "fit": "average_SEM", 
        "value": 8.450501021191788e-05
    }, 
    "H1": {
        "error": 0.11439036159684683, 
        "fit": "average_SEM", 
        "value": -0.2548556914378423
    }, 
    "H2": {
        "error": 0.12048296960045955, 
        "fit": "average_SEM", 
        "value": -0.4771197237074375
    }, 
    "L1": {
        "error": 0.16300349701094632, 
        "fit": "average_SEM", 
        "value": -0.32441966407350264
    }, 
    "L2": {
        "error": 0.1297804335684605, 
        "fit": "average_SEM", 
        "value": -0.42571789442251123
    }
}