{
    "Ar36": {
        "error": 0.0030301924768378996, 
        "fit": "parabolic", 
        "value": 0.054174861506625566
    }, 
    "Ar37": {
        "error": 0.2346919047305247, 
        "fit": "linear", 
        "value": 6.3438057040429996
    }, 
    "Ar38": {
        "error": 0.1134713894285764, 
        "fit": "linear", 
        "value": -0.20403042119770293
    }, 
    "Ar39": {
        "error": 0.060174137331855143, 
        "fit": "parabolic", 
        "value": 3.8415501582826268
    }, 
    "Ar40": {
        "error": 0.14023129147721861, 
        "fit": "parabolic", 
        "value": 56.485335338910211
    }, 
    "Ar41": {
        "error": 0.11445691562785845, 
        "fit": "average_SEM", 
        "value": -0.41488731593592093
    }
}